django_unique_upload-0.2.1.dist-info/DESCRIPTION.rst
django_unique_upload-0.2.1.dist-info/METADATA
django_unique_upload-0.2.1.dist-info/RECORD
django_unique_upload-0.2.1.dist-info/WHEEL
django_unique_upload-0.2.1.dist-info/metadata.json
django_unique_upload-0.2.1.dist-info/top_level.txt
unique_upload/__init__.py
unique_upload/unique_upload.py
